yamlloader/__init__.py
yamlloader/_version.py
yamlloader/settings.py
yamlloader/ordereddict/__init__.py
yamlloader/ordereddict/dumpers.py
yamlloader/ordereddict/loaders.py
yamlloader-1.5.2.dist-info/METADATA
yamlloader-1.5.2.dist-info/WHEEL
yamlloader-1.5.2.dist-info/licenses/LICENSE
yamlloader-1.5.2.dist-info/RECORD
