Metadata-Version: 2.4
Name: yamlloader
Version: 1.5.2
Summary: Ordered YAML loader and dumper for PyYAML.
Project-URL: Documentation, https://yamlloader.readthedocs.io/
Project-URL: Homepage, https://github.com/Phynix/yamlloader
Author-email: Jonas Eschle <jonas.eschle@gmail.com>, Johannes Lade <johannes.lade@phynix.science>
Maintainer-email: Jonas Eschle <jonas.eschle@gmail.com>
License: Copyright 2017 Jonas Eschle
License-File: LICENSE
Keywords: PyYAML,dict,dumper,loader,ordered,yaml
Classifier: Development Status :: 5 - Production/Stable
Classifier: Intended Audience :: Developers
Classifier: Intended Audience :: Science/Research
Classifier: Intended Audience :: System Administrators
Classifier: License :: OSI Approved :: MIT License
Classifier: Natural Language :: English
Classifier: Programming Language :: Python
Classifier: Programming Language :: Python :: 3 :: Only
Classifier: Programming Language :: Python :: 3.7
Classifier: Programming Language :: Python :: 3.8
Classifier: Programming Language :: Python :: 3.9
Classifier: Programming Language :: Python :: 3.10
Classifier: Programming Language :: Python :: 3.11
Classifier: Programming Language :: Python :: 3.12
Classifier: Programming Language :: Python :: 3.13
Classifier: Topic :: Software Development :: Libraries
Classifier: Topic :: Utilities
Requires-Python: >=3.7
Requires-Dist: pyyaml
Provides-Extra: dev
Requires-Dist: coverage; extra == 'dev'
Requires-Dist: hypothesis; extra == 'dev'
Requires-Dist: sphinx; extra == 'dev'
Requires-Dist: sphinx-autodoc-typehints; extra == 'dev'
Requires-Dist: sphinx-rtd-theme; extra == 'dev'
Requires-Dist: sphinxcontrib-apidoc; extra == 'dev'
Provides-Extra: doc
Requires-Dist: sphinx; extra == 'doc'
Requires-Dist: sphinx-autodoc-typehints; extra == 'doc'
Requires-Dist: sphinx-rtd-theme; extra == 'doc'
Requires-Dist: sphinxcontrib-apidoc; extra == 'doc'
Provides-Extra: test
Requires-Dist: coverage; extra == 'test'
Requires-Dist: hypothesis; extra == 'test'
